EasyFileHandler/__init__.py
EasyFileHandler/code.py
EasyFileHandler-1.6.dist-info/LICENSE
EasyFileHandler-1.6.dist-info/METADATA
EasyFileHandler-1.6.dist-info/WHEEL
EasyFileHandler-1.6.dist-info/top_level.txt
EasyFileHandler-1.6.dist-info/RECORD
