Metadata-Version: 2.1
Name: EasyFileHandler
Version: 1.6
Summary: File Operations' Controller. Has Edit, Write(Format) And Read Features
Home-page: https://github.com/v1s1t0r999/PyPi_Uploads/tree/EasyFileHandler
Author: v1s1t0r999
Author-email: aditya.funs.11@gmail.com
License: MIT
Platform: UNKNOWN
Classifier: License :: OSI Approved :: MIT License
Classifier: Programming Language :: Python :: 3
Classifier: Programming Language :: Python :: 3.7
Requires-Python: >=3.6
